http_file/__init__.py
http_file/download_file.py
http_file-0.1.7.dist-info/LICENSE
http_file-0.1.7.dist-info/METADATA
http_file-0.1.7.dist-info/WHEEL
http_file-0.1.7.dist-info/top_level.txt
http_file-0.1.7.dist-info/RECORD
