Metadata-Version: 2.1
Name: http-file
Version: 0.1.7
Summary: ...
Home-page: https://github.com/RivalStorms/http_file
Author: Tyshko Stanislav
Author-email: admin@toqp.ru
License: UNKNOWN
Platform: UNKNOWN
Classifier: License :: OSI Approved :: MIT License
Requires-Dist: urllib3
Requires-Dist: requests
